marvelcli/__init__.py
marvelcli/marvelcli.py
marvelcli/utils.py
marvelcli/folder/__init__.py
marvelcli/folder/folder_commands.py
marvelcli/folder/folder_queries.py
marvelcli/group/__init__.py
marvelcli/group/group_commands.py
marvelcli/group/group_queries.py
marvelcli/project/__init__.py
marvelcli/project/project_commands.py
marvelcli/project/project_queries.py
marvelcli/user/__init__.py
marvelcli/user/user_commands.py
marvelcli/user/user_queries.py
marvelcli/workspace/__init__.py
marvelcli/workspace/workspace_commands.py
marvelcli/workspace/workspace_queries.py
marvelapp_cli-0.0.1.dist-info/LICENSE
marvelapp_cli-0.0.1.dist-info/METADATA
marvelapp_cli-0.0.1.dist-info/WHEEL
marvelapp_cli-0.0.1.dist-info/entry_points.txt
marvelapp_cli-0.0.1.dist-info/top_level.txt
marvelapp_cli-0.0.1.dist-info/RECORD
