Metadata-Version: 2.1
Name: marvelapp-cli
Version: 0.0.1
Summary: A CLI wrapper for Marvelapp
Home-page: https://github.com/sophiefitzpatrick/marvelcli
Author: Sophie Fitzpatrick
Author-email: sophierfitzpatrick@gmail.com
License: UNKNOWN
Platform: UNKNOWN
Classifier: Programming Language :: Python :: 3
Classifier: License :: OSI Approved :: MIT License
Classifier: Operating System :: OS Independent
Requires-Python: >=3.6
